{
  "jobid": 16258503,
  "calibration": {
    "ra": 83.49711432562825,
    "dec": -2.6096905076740415,
    "width_arcsec": 99122.97970864015,
    "height_arcsec": 68722.91843624489,
    "radius": 16.75221368313403,
    "pixscale": 58.68737697373603,
    "orientation": 37.985207346719335,
    "parity": 1.0
  },
  "objects_in_field": [
    "Part of the constellation Eridanus (Eri)",
    "Part of the constellation Monoceros (Mon)",
    "Part of the constellation Lepus (Lep)",
    "Part of the constellation Orion (Ori)",
    "NGC 1976",
    "M 42",
    "IC 434",
    "NGC 2024",
    "Great Orion Nebula",
    "Orion Nebula",
    "Flame Nebula",
    "Orion B",
    "NGC 1909",
    "the Witch Head Nebula",
    "The star Alnitak (ζ Ori",
    "50 Ori)",
    "The star Bellatrix (γ Ori",
    "24 Ori)",
    "The star Rigel",
    "Algebar (β Ori",
    "19 Ori)",
    "The star Saiph (κ Ori",
    "53 Ori)",
    "The star Mintaka (δ Ori",
    "34 Ori)",
    "The star Cursa",
    "Dhalim (β Eri",
    "67 Eri)",
    "The star Betelgeuse",
    "Al Mankib",
    "Betelgeux (α Ori",
    "58 Ori)",
    "The star Alnilam (ε Ori",
    "46 Ori)",
    "The star Hatysa (ι Ori",
    "44 Ori)",
    "The star μ Lep",
    "5 Lep"
  ],
  "tags": [
    "Part of the constellation Eridanus (Eri)",
    "Part of the constellation Monoceros (Mon)",
    "Part of the constellation Lepus (Lep)",
    "Part of the constellation Orion (Ori)",
    "The star Rigel",
    "Algebar (β Ori",
    "19 Ori)",
    "The star Betelgeuse",
    "Al Mankib",
    "Betelgeux (α Ori",
    "58 Ori)",
    "The star Bellatrix (γ Ori",
    "24 Ori)",
    "The star Alnilam (ε Ori",
    "46 Ori)",
    "The star Alnitak (ζ Ori",
    "50 Ori)",
    "The star Saiph (κ Ori",
    "53 Ori)",
    "The star Mintaka (δ Ori",
    "34 Ori)",
    "The star Hatysa (ι Ori",
    "44 Ori)",
    "The star Cursa",
    "Dhalim (β Eri",
    "67 Eri)",
    "The star μ Lep",
    "5 Lep",
    "IC 434",
    "Flame Nebula",
    "Orion B",
    "NGC 1909",
    "the Witch Head Nebula",
    "NGC 1976",
    "Great Orion Nebula",
    "Orion Nebula",
    "M 42",
    "NGC 2024"
  ]
}